tg_file_exporter/__init__.py
tg_file_exporter/__main__.py
tg_file_exporter/search_messages_by_date.py
tg_file_exporter-1.1.17.dist-info/METADATA
tg_file_exporter-1.1.17.dist-info/WHEEL
tg_file_exporter-1.1.17.dist-info/entry_points.txt
tg_file_exporter-1.1.17.dist-info/top_level.txt
tg_file_exporter-1.1.17.dist-info/RECORD
