Metadata-Version: 2.4
Name: tg-file-exporter
Version: 1.1.17
Summary: Download all files from Telegram chat
Author-email: Alexey <aleks-samos@yandex.ru>
Requires-Python: <3.12,>=3.9.0
Requires-Dist: kurigram>=2.2.12
Requires-Dist: loguru>=0.7.3
Requires-Dist: tgcrypto>=1.2.5
Requires-Dist: wxasync>=0.49
Requires-Dist: wxwidgets>=1.0.5
